[
    {
        "Norwegian": "Aldri",
        "English": "Never"
    },
    {
        "Norwegian": "Av Og Til",
        "English": "Sometimes"
    },
    {
        "Norwegian": "Bare Hyggelig",
        "English": "You'Re Welcome"
    },
    {
        "Norwegian": "Beklager",
        "English": "Sorry"
    },
    {
        "Norwegian": "Bra",
        "English": "Alright"
    },
    {
        "Norwegian": "Bror",
        "English": "Brother"
    },
    {
        "Norwegian": "Broren",
        "English": "The Brother"
    },
    {
        "Norwegian": "Brød",
        "English": "Bread"
    },
    {
        "Norwegian": "Dag",
        "English": "Day"
    },
    {
        "Norwegian": "Datteren",
        "English": "The Daughter"
    },
    {
        "Norwegian": "Det",
        "English": "It"
    },
    {
        "Norwegian": "Din",
        "English": "Your"
    },
    {
        "Norwegian": "Du",
        "English": "You"
    },
    {
        "Norwegian": "Egg",
        "English": "Egg"
    },
    {
        "Norwegian": "Egget",
        "English": "The Egg"
    },
    {
        "Norwegian": "Eller",
        "English": "Or"
    },
    {
        "Norwegian": "En",
        "English": "A"
    },
    {
        "Norwegian": "Er",
        "English": "Is"
    },
    {
        "Norwegian": "Et",
        "English": "An"
    },
    {
        "Norwegian": "Far",
        "English": "Father"
    },
    {
        "Norwegian": "Faren",
        "English": "The Father"
    },
    {
        "Norwegian": "Fisk",
        "English": "Fish"
    },
    {
        "Norwegian": "Fisken",
        "English": "The Fish"
    },
    {
        "Norwegian": "For",
        "English": "Too"
    },
    {
        "Norwegian": "Gitar",
        "English": "Guitar"
    },
    {
        "Norwegian": "God",
        "English": "Good"
    },
    {
        "Norwegian": "God Dag",
        "English": "Good Afternoon"
    },
    {
        "Norwegian": "God Helg",
        "English": "Good Weekend"
    },
    {
        "Norwegian": "God Kveld",
        "English": "Good Evening"
    },
    {
        "Norwegian": "God Morgen",
        "English": "Good Morning"
    },
    {
        "Norwegian": "Godt",
        "English": "Good"
    },
    {
        "Norwegian": "Gutten",
        "English": "The Boy"
    },
    {
        "Norwegian": "Går Det Bra",
        "English": "Are You Alright?"
    },
    {
        "Norwegian": "Går Det Bra Med Deg",
        "English": "Are You Doing Alright?"
    },
    {
        "Norwegian": "Ha Det",
        "English": "Goodbye",
        "Type": "Casual"
    },
    {
        "Norwegian": "Ha Det Bra",
        "English": "Goodbye",
        "Type": "Formal"
    },
    {
        "Norwegian": "Hallo",
        "English": "Hello"
    },
    {
        "Norwegian": "Han",
        "English": "He"
    },
    {
        "Norwegian": "Har",
        "English": "Have"
    },
    {
        "Norwegian": "Hei",
        "English": "Hi"
    },
    {
        "Norwegian": "Her",
        "English": "Here"
    },
    {
        "Norwegian": "Horer",
        "English": "Whore"
    },
    {
        "Norwegian": "Hun",
        "English": "She"
    },
    {
        "Norwegian": "Hund",
        "English": "Dog"
    },
    {
        "Norwegian": "Hunden",
        "English": "The Dog"
    },
    {
        "Norwegian": "Hvor",
        "English": "Where"
    },
    {
        "Norwegian": "Hvordan Går Det",
        "English": "How Are You?"
    },
    {
        "Norwegian": "Hører",
        "English": "Listens"
    },
    {
        "Norwegian": "Høy",
        "English": "Tall"
    },
    {
        "Norwegian": "Interessant",
        "English": "Interesting"
    },
    {
        "Norwegian": "Ja",
        "English": "Yes"
    },
    {
        "Norwegian": "Jeg",
        "English": "I"
    },
    {
        "Norwegian": "Jenta",
        "English": "The Girl"
    },
    {
        "Norwegian": "Jobb",
        "English": "Job"
    },
    {
        "Norwegian": "Jobben",
        "English": "Jobs"
    },
    {
        "Norwegian": "Kaffe",
        "English": "Coffee"
    },
    {
        "Norwegian": "Kaffen",
        "English": "The Coffee"
    },
    {
        "Norwegian": "Kald",
        "English": "Cold"
    },
    {
        "Norwegian": "Kanskje",
        "English": "Maybe"
    },
    {
        "Norwegian": "Katt",
        "English": "Cat"
    },
    {
        "Norwegian": "Katten",
        "English": "The Cat"
    },
    {
        "Norwegian": "Kvinnen",
        "English": "The Woman"
    },
    {
        "Norwegian": "Lager",
        "English": "Lower"
    },
    {
        "Norwegian": "Lege",
        "English": "Doctor"
    },
    {
        "Norwegian": "Legen",
        "English": "The Doctor"
    },
    {
        "Norwegian": "Leser",
        "English": "Reader"
    },
    {
        "Norwegian": "Lærer",
        "English": "Teacher"
    },
    {
        "Norwegian": "Maler",
        "English": "Painter"
    },
    {
        "Norwegian": "Mannen",
        "English": "The Man"
    },
    {
        "Norwegian": "Maten",
        "English": "The Food"
    },
    {
        "Norwegian": "Med",
        "English": "With"
    },
    {
        "Norwegian": "Melk",
        "English": "Milk"
    },
    {
        "Norwegian": "Men",
        "English": "But"
    },
    {
        "Norwegian": "Meny",
        "English": "Menu"
    },
    {
        "Norwegian": "Menyen",
        "English": "The Menu"
    },
    {
        "Norwegian": "Mer",
        "English": "More"
    },
    {
        "Norwegian": "Min",
        "English": "My"
    },
    {
        "Norwegian": "Mor",
        "English": "Mother"
    },
    {
        "Norwegian": "Moren",
        "English": "The Mother"
    },
    {
        "Norwegian": "Morsom",
        "English": "Funny"
    },
    {
        "Norwegian": "Musikk",
        "English": "Music"
    },
    {
        "Norwegian": "Nei",
        "English": "No"
    },
    {
        "Norwegian": "Ofte",
        "English": "Often"
    },
    {
        "Norwegian": "Og",
        "English": "And"
    },
    {
        "Norwegian": "Ost",
        "English": "Cheese"
    },
    {
        "Norwegian": "Osten",
        "English": "The Cheese"
    },
    {
        "Norwegian": "Pa",
        "English": "Pa"
    },
    {
        "Norwegian": "Pizza",
        "English": "Pizza"
    },
    {
        "Norwegian": "Pizzaen",
        "English": "The Pizza"
    },
    {
        "Norwegian": "Professor",
        "English": "Professor"
    },
    {
        "Norwegian": "På",
        "English": "To"
    },
    {
        "Norwegian": "Regningen",
        "English": "The Bill"
    },
    {
        "Norwegian": "Restaurant",
        "English": "Restaurant"
    },
    {
        "Norwegian": "Restauranten",
        "English": "The Restaurant"
    },
    {
        "Norwegian": "Salaten",
        "English": "The Salad"
    },
    {
        "Norwegian": "Smart",
        "English": "Smart"
    },
    {
        "Norwegian": "Snill",
        "English": "Nice"
    },
    {
        "Norwegian": "Spiller",
        "English": "Plays"
    },
    {
        "Norwegian": "Stressende",
        "English": "Stressful"
    },
    {
        "Norwegian": "Student",
        "English": "Student"
    },
    {
        "Norwegian": "Svommer",
        "English": "Swims"
    },
    {
        "Norwegian": "Sykepleier",
        "English": "Nurse"
    },
    {
        "Norwegian": "Sønnen",
        "English": "The Son"
    },
    {
        "Norwegian": "Søster",
        "English": "Sister"
    },
    {
        "Norwegian": "Søsteren",
        "English": "The Sister"
    },
    {
        "Norwegian": "Takk",
        "English": "Thanks"
    },
    {
        "Norwegian": "Te",
        "English": "Tea"
    },
    {
        "Norwegian": "Teen",
        "English": "The Tea"
    },
    {
        "Norwegian": "Tusen Takk",
        "English": "Thank You Very Much"
    },
    {
        "Norwegian": "Ung",
        "English": "Young"
    },
    {
        "Norwegian": "Unnskyld",
        "English": "Sorry"
    },
    {
        "Norwegian": "Vann",
        "English": "Water"
    },
    {
        "Norwegian": "Vanskelig",
        "English": "Difficult"
    },
    {
        "Norwegian": "Varm",
        "English": "Warm"
    },
    {
        "Norwegian": "Veldig",
        "English": "Very"
    },
    {
        "Norwegian": "Velkommen",
        "English": "Welcome"
    },
    {
        "Norwegian": "Vin",
        "English": "Wine"
    },
    {
        "Norwegian": "Vær Så Snill",
        "English": "Please"
    },
    {
        "Norwegian": "Å",
        "English": "Oh"
    }
]